rxinferclient/__init__.py
rxinferclient/api_client.py
rxinferclient/api_response.py
rxinferclient/configuration.py
rxinferclient/exceptions.py
rxinferclient/rest.py
rxinferclient/api/__init__.py
rxinferclient/api/authentication_api.py
rxinferclient/api/models_api.py
rxinferclient/api/server_api.py
rxinferclient/models/__init__.py
rxinferclient/models/attach_events_to_episode_request.py
rxinferclient/models/attach_events_to_episode_request_events_inner.py
rxinferclient/models/attach_metadata_to_event_request.py
rxinferclient/models/available_model.py
rxinferclient/models/available_model_details.py
rxinferclient/models/create_episode_request.py
rxinferclient/models/create_model_instance_request.py
rxinferclient/models/create_model_instance_response.py
rxinferclient/models/delete_model_instance_request.py
rxinferclient/models/episode_info.py
rxinferclient/models/error_response.py
rxinferclient/models/infer_request.py
rxinferclient/models/infer_response.py
rxinferclient/models/learn_request.py
rxinferclient/models/learn_response.py
rxinferclient/models/model_instance.py
rxinferclient/models/model_instance_parameters.py
rxinferclient/models/model_instance_state.py
rxinferclient/models/not_found_response.py
rxinferclient/models/ping_response.py
rxinferclient/models/server_info.py
rxinferclient/models/success_response.py
rxinferclient/models/token_generate_response.py
rxinferclient/models/token_roles_response.py
rxinferclient/models/unauthorized_response.py
rxinferclient/test/__init__.py
rxinferclient/test/test_attach_events_to_episode_request.py
rxinferclient/test/test_attach_events_to_episode_request_events_inner.py
rxinferclient/test/test_attach_metadata_to_event_request.py
rxinferclient/test/test_authentication_api.py
rxinferclient/test/test_available_model.py
rxinferclient/test/test_available_model_details.py
rxinferclient/test/test_create_episode_request.py
rxinferclient/test/test_create_model_instance_request.py
rxinferclient-0.1.2.dist-info/METADATA
rxinferclient-0.1.2.dist-info/WHEEL
rxinferclient-0.1.2.dist-info/licenses/LICENSE
rxinferclient-0.1.2.dist-info/RECORD
