Metadata-Version: 2.4
Name: rxinferclient
Version: 0.1.2
Summary: The official Python library for the RxInferServer API
Project-URL: Homepage, https://github.com/lazydynamics/RxInferClient.py
Project-URL: Repository, https://github.com/lazydynamics/RxInferClient.py
Project-URL: Issues, https://github.com/lazydynamics/RxInferClient.py/issues
Author-email: Lazy Dynamics <info@lazydynamics.com>
License-Expression: Apache-2.0
License-File: LICENSE
Classifier: Intended Audience :: Developers
Classifier: License :: OSI Approved :: Apache Software License
Classifier: Operating System :: OS Independent
Classifier: Programming Language :: Python :: 3
Requires-Python: >=3.9
Requires-Dist: niquests
Requires-Dist: pydantic>=2
Requires-Dist: python-dateutil>=2.8.2
Requires-Dist: typing-extensions>=4.7.1
Requires-Dist: urllib3<3.0.0,>=2.1.0
Provides-Extra: dev
Requires-Dist: black; extra == 'dev'
Requires-Dist: hatchling; extra == 'dev'
Requires-Dist: isort; extra == 'dev'
Requires-Dist: mkdocs; extra == 'dev'
Requires-Dist: mkdocs-gen-files; extra == 'dev'
Requires-Dist: mkdocs-literate-nav; extra == 'dev'
Requires-Dist: mkdocs-material; extra == 'dev'
Requires-Dist: mkdocs-render-swagger-plugin; extra == 'dev'
Requires-Dist: mkdocstrings[python]; extra == 'dev'
Requires-Dist: mypy; extra == 'dev'
Requires-Dist: pymdown-extensions; extra == 'dev'
Requires-Dist: pytest; extra == 'dev'
Requires-Dist: pytest-asyncio; extra == 'dev'
Requires-Dist: pytest-cov; extra == 'dev'
Requires-Dist: pytest-mock; extra == 'dev'
Requires-Dist: tenacity; extra == 'dev'
Requires-Dist: twine; extra == 'dev'
